<?xml version="1.0" encoding="utf-8" ?>
<dwsync>
<file name="CalculatedFieldExamples.da.resx" server="173.203.189.72//vulcan/" local="130433353266211090" remote="129182832000000000" Dst="2" />
<file name="CalculatedFieldExamples.ar.resx" server="173.203.189.72//vulcan/" local="130433353266211090" remote="129182832000000000" Dst="2" />
<file name="CalculatedFieldExamples.de.resx" server="173.203.189.72//vulcan/" local="130433353266991095" remote="129182832000000000" Dst="2" />
<file name="CalculatedFieldExamples.es.resx" server="173.203.189.72//vulcan/" local="130433353266991095" remote="129182832000000000" Dst="2" />
<file name="CalculatedFieldExamples.fr.resx" server="173.203.189.72//vulcan/" local="130433353267615099" remote="129182832000000000" Dst="2" />
<file name="CalculatedFieldExamples.he.resx" server="173.203.189.72//vulcan/" local="130433353267615099" remote="129182832000000000" Dst="2" />
<file name="CalculatedFieldExamples.it.resx" server="173.203.189.72//vulcan/" local="130433353268395104" remote="129182832000000000" Dst="2" />
<file name="CalculatedFieldExamples.ja.resx" server="173.203.189.72//vulcan/" local="130433353268395104" remote="129182832000000000" Dst="2" />
<file name="CalculatedFieldExamples.ko.resx" server="173.203.189.72//vulcan/" local="130433353269019108" remote="129182832000000000" Dst="2" />
<file name="CalculatedFieldExamples.nl.resx" server="173.203.189.72//vulcan/" local="130433353269019108" remote="129182832000000000" Dst="2" />
<file name="CalculatedFieldExamples.pt.resx" server="173.203.189.72//vulcan/" local="130433353269643112" remote="129182832000000000" Dst="2" />
<file name="CalculatedFieldExamples.resx" server="173.203.189.72//vulcan/" local="130433353269643112" remote="129182832000000000" Dst="2" />
<file name="CalculatedFieldExamples.ru.resx" server="173.203.189.72//vulcan/" local="130433353269955114" remote="129182832000000000" Dst="2" />
<file name="CalculatedFieldExamples.sv.resx" server="173.203.189.72//vulcan/" local="130433353281499188" remote="129182832000000000" Dst="2" />
<file name="CalculatedFieldExamples.zh-chs.resx" server="173.203.189.72//vulcan/" local="130433353281967191" remote="129182832000000000" Dst="2" />
<file name="CalculatedFieldExamples.zh-cht.resx" server="173.203.189.72//vulcan/" local="130433353281967191" remote="129182832000000000" Dst="2" />
<file name="ChoicesFieldDialog.resx" server="173.203.189.72//vulcan/" local="130433353282591195" remote="129182832000000000" Dst="2" />
<file name="DataListSpec.ar.resx" server="173.203.189.72//vulcan/" local="130433353282591195" remote="129182832000000000" Dst="2" />
<file name="CompatibilityReport.resx" server="173.203.189.72//vulcan/" local="130433353282747196" remote="129182832000000000" Dst="2" />
<file name="DataListSpec.de.resx" server="173.203.189.72//vulcan/" local="130433353283527201" remote="129182832000000000" Dst="2" />
<file name="DataListSpec.da.resx" server="173.203.189.72//vulcan/" local="130433353283683202" remote="129182832000000000" Dst="2" />
<file name="DataListSpec.es.resx" server="173.203.189.72//vulcan/" local="130433353284307206" remote="129182832000000000" Dst="2" />
<file name="DataListSpec.he.resx" server="173.203.189.72//vulcan/" local="130433353284307206" remote="129182832000000000" Dst="2" />
<file name="DataListSpec.fr.resx" server="173.203.189.72//vulcan/" local="130433353285399213" remote="129182832000000000" Dst="2" />
<file name="DataListSpec.it.resx" server="173.203.189.72//vulcan/" local="130433353286023217" remote="129182832000000000" Dst="2" />
<file name="DataListSpec.ja.resx" server="173.203.189.72//vulcan/" local="130433353286023217" remote="129182832000000000" Dst="2" />
<file name="DataListSpec.ko.resx" server="173.203.189.72//vulcan/" local="130433353286647221" remote="129182832000000000" Dst="2" />
<file name="DataListSpec.nl.resx" server="173.203.189.72//vulcan/" local="130433353286647221" remote="129182832000000000" Dst="2" />
<file name="DataListSpec.pt.resx" server="173.203.189.72//vulcan/" local="130433353287427226" remote="129182832000000000" Dst="2" />
<file name="DataListSpec.ru.resx" server="173.203.189.72//vulcan/" local="130433353287427226" remote="129182832000000000" Dst="2" />
<file name="DataListSpec.resx" server="173.203.189.72//vulcan/" local="130433353288051230" remote="129182832000000000" Dst="2" />
<file name="DataListSpec.sv.resx" server="173.203.189.72//vulcan/" local="130433353288051230" remote="129182832000000000" Dst="2" />
<file name="DataListSpec.zh-chs.resx" server="173.203.189.72//vulcan/" local="130433353288675234" remote="129182832000000000" Dst="2" />
<file name="FontName.ar.resx" server="173.203.189.72//vulcan/" local="130433353288831235" remote="129182832000000000" Dst="2" />
<file name="DataListSpec.zh-cht.resx" server="173.203.189.72//vulcan/" local="130433353289455239" remote="129182832000000000" Dst="2" />
<file name="FontName.da.resx" server="173.203.189.72//vulcan/" local="130433353289455239" remote="129182832000000000" Dst="2" />
<file name="FontName.de.resx" server="173.203.189.72//vulcan/" local="130433353289923242" remote="129182832000000000" Dst="2" />
<file name="FontName.es.resx" server="173.203.189.72//vulcan/" local="130433353290079243" remote="129182832000000000" Dst="2" />
<file name="FontName.fr.resx" server="173.203.189.72//vulcan/" local="130433353302247321" remote="129182832000000000" Dst="2" />
<file name="FontName.he.resx" server="173.203.189.72//vulcan/" local="130433353302403322" remote="129182832000000000" Dst="2" />
<file name="FontName.it.resx" server="173.203.189.72//vulcan/" local="130433353303027326" remote="129182832000000000" Dst="2" />
<file name="FontName.ko.resx" server="173.203.189.72//vulcan/" local="130433353303027326" remote="129182832000000000" Dst="2" />
<file name="FontName.ja.resx" server="173.203.189.72//vulcan/" local="130433353303027326" remote="129182832000000000" Dst="2" />
<file name="FontName.nl.resx" server="173.203.189.72//vulcan/" local="130433353304119333" remote="129182832000000000" Dst="2" />
<file name="FontName.pt.resx" server="173.203.189.72//vulcan/" local="130433353304275334" remote="129182832000000000" Dst="2" />
<file name="FontName.resx" server="173.203.189.72//vulcan/" local="130433353304899338" remote="129182832000000000" Dst="2" />
<file name="FontName.ru.resx" server="173.203.189.72//vulcan/" local="130433353304899338" remote="129182832000000000" Dst="2" />
<file name="FontName.sv.resx" server="173.203.189.72//vulcan/" local="130433353304899338" remote="129182832000000000" Dst="2" />
<file name="FontName.zh-chs.resx" server="173.203.189.72//vulcan/" local="130433353305835344" remote="129182832000000000" Dst="2" />
<file name="FontName.zh-cht.resx" server="173.203.189.72//vulcan/" local="130433353305835344" remote="129182832000000000" Dst="2" />
<file name="FontSize.ar.resx" server="173.203.189.72//vulcan/" local="130433353305835344" remote="129182832000000000" Dst="2" />
<file name="FontSize.de.resx" server="173.203.189.72//vulcan/" local="130433353306771350" remote="129182832000000000" Dst="2" />
<file name="FontSize.da.resx" server="173.203.189.72//vulcan/" local="130433353306927351" remote="129182832000000000" Dst="2" />
<file name="FontSize.es.resx" server="173.203.189.72//vulcan/" local="130433353306927351" remote="129182832000000000" Dst="2" />
<file name="FontSize.fr.resx" server="173.203.189.72//vulcan/" local="130433353308175359" remote="129182832000000000" Dst="2" />
<file name="FontSize.he.resx" server="173.203.189.72//vulcan/" local="130433353308175359" remote="129182832000000000" Dst="2" />
<file name="FontSize.it.resx" server="173.203.189.72//vulcan/" local="130433353308955364" remote="129182832000000000" Dst="2" />
<file name="FontSize.ko.resx" server="173.203.189.72//vulcan/" local="130433353308955364" remote="129182832000000000" Dst="2" />
<file name="FontSize.ja.resx" server="173.203.189.72//vulcan/" local="130433353309579368" remote="129182832000000000" Dst="2" />
<file name="FontSize.nl.resx" server="173.203.189.72//vulcan/" local="130433353309579368" remote="129182832000000000" Dst="2" />
<file name="FontSize.pt.resx" server="173.203.189.72//vulcan/" local="130433353309735369" remote="129182832000000000" Dst="2" />
<file name="FontSize.resx" server="173.203.189.72//vulcan/" local="130433353310359373" remote="129182832000000000" Dst="2" />
<file name="FontSize.ru.resx" server="173.203.189.72//vulcan/" local="130433353321435444" remote="129182832000000000" Dst="2" />
<file name="FontSize.zh-chs.resx" server="173.203.189.72//vulcan/" local="130433353321435444" remote="129182832000000000" Dst="2" />
<file name="FontSize.sv.resx" server="173.203.189.72//vulcan/" local="130433353322215449" remote="129182832000000000" Dst="2" />
<file name="FontSize.zh-cht.resx" server="173.203.189.72//vulcan/" local="130433353322215449" remote="129182832000000000" Dst="2" />
<file name="RelevantExamples.resx" server="173.203.189.72//vulcan/" local="130433353322527451" remote="129182832000000000" Dst="2" />
<file name="ValidateSpec.da.resx" server="173.203.189.72//vulcan/" local="130433353323151455" remote="129182832000000000" Dst="2" />
<file name="ValidateSpec.ar.resx" server="173.203.189.72//vulcan/" local="130433353323151455" remote="129182832000000000" Dst="2" />
<file name="ValidateSpec.de.resx" server="173.203.189.72//vulcan/" local="130433353323775459" remote="129182832000000000" Dst="2" />
<file name="ValidateSpec.es.resx" server="173.203.189.72//vulcan/" local="130433353323931460" remote="129182832000000000" Dst="2" />
<file name="ValidateSpec.fr.resx" server="173.203.189.72//vulcan/" local="130433353324867466" remote="129182832000000000" Dst="2" />
<file name="ValidateSpec.he.resx" server="173.203.189.72//vulcan/" local="130433353325335469" remote="129182832000000000" Dst="2" />
<file name="ValidateSpec.it.resx" server="173.203.189.72//vulcan/" local="130433353325335469" remote="129182832000000000" Dst="2" />
<file name="ValidateSpec.ja.resx" server="173.203.189.72//vulcan/" local="130433353326115474" remote="129182832000000000" Dst="2" />
<file name="ValidateSpec.ko.resx" server="173.203.189.72//vulcan/" local="130433353326115474" remote="129182832000000000" Dst="2" />
<file name="ValidateSpec.nl.resx" server="173.203.189.72//vulcan/" local="130433353327363482" remote="129182832000000000" Dst="2" />
<file name="ValidateSpec.resx" server="173.203.189.72//vulcan/" local="130433353327363482" remote="129182832000000000" Dst="2" />
<file name="ValidateSpec.pt.resx" server="173.203.189.72//vulcan/" local="130433353327987486" remote="129182832000000000" Dst="2" />
<file name="ValidateSpec.ru.resx" server="173.203.189.72//vulcan/" local="130433353327987486" remote="129182832000000000" Dst="2" />
<file name="ValidateSpec.sv.resx" server="173.203.189.72//vulcan/" local="130433353328767491" remote="129182832000000000" Dst="2" />
<file name="ValidateSpec.zh-cht.resx" server="173.203.189.72//vulcan/" local="130433353328767491" remote="129182832000000000" Dst="2" />
<file name="ValidateSpec.zh-chs.resx" server="173.203.189.72//vulcan/" local="130433353329235494" remote="129182832000000000" Dst="2" />
</dwsync>